{
	"id": "52e8fff3-5849-4830-b45c-4d018b3ce144",
	"name": "JSON Data - locally",
	"values": [
		{
			"key": "jsonDataApiUrl",
			"value": "http://localhost:8087",
			"type": "default",
			"enabled": true
		},
		{
			"key": "appId",
			"value": "",
			"type": "default",
			"enabled": true
		},
		{
			"key": "updatedAppId",
			"value": "",
			"type": "default",
			"enabled": true
		}
	],
	"_postman_variable_scope": "environment",
	"_postman_exported_at": "2024-08-15T03:23:55.415Z",
	"_postman_exported_using": "Postman/11.8.0"
}